Workbook
Name SegmentaciónDeDatos_Canal_Venta: #N/A
Name SegmentaciónDeDatos_Ciudad: #N/A
Name SegmentaciónDeDatos_Descuento: #N/A

Sheet Ventas_2026
A1: ID_Venta | B1: Fecha | C1: Ciudad | D1: Canal_Venta | E1: SKU | F1: Cantidad | G1: Descuento_% | H1: Producto | I1: Categoría | J1: Precio_Unitario | K1: Total_Bruto | L1: Total_Neto | M1: Fuga de ingresos
A2: VEN-2001 | B2: 2026-03-05 | C2: Bucaramanga | D2: Distribuidor | E2: PROD-108 | F2: 4 | G2: 0.05 | H2: {=_xlfn.XLOOKUP(E2,Catálogo_Productos!$A:$A,Catálogo_Productos!$B:$D,"producto no encontrado")} -> Micrófono USB Studio | I2: Audio | J2: 130 | K2: =F2*J2 -> 520 | L2: =K2*(1-G2) -> 494 | M2: =K2-L2 -> 26
A3: VEN-2002 | B3: 2026-05-13 | C3: Bogotá | D3: Sitio Web | E3: PROD-108 | F3: 2 | G3: 0.1 | H3: {=_xlfn.XLOOKUP(E3,Catálogo_Productos!$A:$A,Catálogo_Productos!$B:$D,"producto no encontrado")} -> Micrófono USB Studio | I3: Audio | J3: 130 | K3: =F3*J3 -> 260 | L3: =K3*(1-G3) -> 234 | M3: =K3-L3 -> 26
A4: VEN-2003 | B4: 2026-01-06 | C4: Pasto | D4: Sitio Web | E4: PROD-105 | F4: 5 | G4: 0 | H4: {=_xlfn.XLOOKUP(E4,Catálogo_Productos!$A:$A,Catálogo_Productos!$B:$D,"producto no encontrado")} -> Silla Ergonómica | I4: Mobiliario | J4: 280 | K4: =F4*J4 -> 1400 | L4: =K4*(1-G4) -> 1400 | M4: =K4-L4 -> 0
A5: VEN-2004 | B5: 2026-05-17 | C5: Barranquilla | D5: Sitio Web | E5: PROD-101 | F5: 2 | G5: 0 | H5: {=_xlfn.XLOOKUP(E5,Catálogo_Productos!$A:$A,Catálogo_Productos!$B:$D,"producto no encontrado")} -> Laptop Pro 15 | I5: Tecnología | J5: 1200 | K5: =F5*J5 -> 2400 | L5: =K5*(1-G5) -> 2400 | M5: =K5-L5 -> 0
A6: VEN-2005 | B6: 2026-03-14 | C6: Medellín | D6: Distribuidor | E6: PROD-104 | F6: 4 | G6: 0.1 | H6: {=_xlfn.XLOOKUP(E6,Catálogo_Productos!$A:$A,Catálogo_Productos!$B:$D,"producto no encontrado")} -> Mouse Inalámbrico Pro | I6: Accesorios | J6: 45 | K6: =F6*J6 -> 180 | L6: =K6*(1-G6) -> 162 | M6: =K6-L6 -> 18
A7: VEN-2006 | B7: 2026-04-18 | C7: Bogotá | D7: Sitio Web | E7: PROD-107 | F7: 3 | G7: 0.05 | H7: {=_xlfn.XLOOKUP(E7,Catálogo_Productos!$A:$A,Catálogo_Productos!$B:$D,"producto no encontrado")} -> Audífonos Noise Cancelling | I7: Audio | J7: 190 | K7: =F7*J7 -> 570 | L7: =K7*(1-G7) -> 541.5 | M7: =K7-L7 -> 28.5
A8: VEN-2007 | B8: 2026-03-04 | C8: Pasto | D8: Distribuidor | E8: PROD-108 | F8: 2 | G8: 0 | H8: {=_xlfn.XLOOKUP(E8,Catálogo_Productos!$A:$A,Catálogo_Productos!$B:$D,"producto no encontrado")} -> Micrófono USB Studio | I8: Audio | J8: 130 | K8: =F8*J8 -> 260 | L8: =K8*(1-G8) -> 260 | M8: =K8-L8 -> 0
A9: VEN-2008 | B9: 2026-05-19 | C9: Pasto | D9: Tienda Física | E9: PROD-104 | F9: 5 | G9: 0 | H9: {=_xlfn.XLOOKUP(E9,Catálogo_Productos!$A:$A,Catálogo_Productos!$B:$D,"producto no encontrado")} -> Mouse Inalámbrico Pro | I9: Accesorios | J9: 45 | K9: =F9*J9 -> 225 | L9: =K9*(1-G9) -> 225 | M9: =K9-L9 -> 0
A10: VEN-2009 | B10: 2026-06-30 | C10: Cali | D10: Distribuidor | E10: PROD-108 | F10: 7 | G10: 0.1 | H10: {=_xlfn.XLOOKUP(E10,Catálogo_Productos!$A:$A,Catálogo_Productos!$B:$D,"producto no encontrado")} -> Micrófono USB Studio | I10: Audio | J10: 130 | K10: =F10*J10 -> 910 | L10: =K10*(1-G10) -> 819 | M10: =K10-L10 -> 91
A11: VEN-2010 | B11: 2026-04-17 | C11: Pasto | D11: Sitio Web | E11: PROD-108 | F11: 5 | G11: 0.05 | H11: {=_xlfn.XLOOKUP(E11,Catálogo_Productos!$A:$A,Catálogo_Productos!$B:$D,"producto no encontrado")} -> Micrófono USB Studio | I11: Audio | J11: 130 | K11: =F11*J11 -> 650 | L11: =K11*(1-G11) -> 617.5 | M11: =K11-L11 -> 32.5
A12: VEN-2011 | B12: 2026-04-08 | C12: Bucaramanga | D12: Tienda Física | E12: PROD-101 | F12: 4 | G12: 0.15 | H12: {=_xlfn.XLOOKUP(E12,Catálogo_Productos!$A:$A,Catálogo_Productos!$B:$D,"producto no encontrado")} -> Laptop Pro 15 | I12: Tecnología | J12: 1200 | K12: =F12*J12 -> 4800 | L12: =K12*(1-G12) -> 4080 | M12: =K12-L12 -> 720
A13: VEN-2012 | B13: 2026-06-13 | C13: Cali | D13: Distribuidor | E13: PROD-105 | F13: 5 | G13: 0 | H13: {=_xlfn.XLOOKUP(E13,Catálogo_Productos!$A:$A,Catálogo_Productos!$B:$D,"producto no encontrado")} -> Silla Ergonómica | I13: Mobiliario | J13: 280 | K13: =F13*J13 -> 1400 | L13: =K13*(1-G13) -> 1400 | M13: =K13-L13 -> 0
... A251: VEN-2250 | B251: 2026-07-20 | C251: Pasto | D251: Tienda Física | E251: PROD-104 | F251: 1 | G251: 0.05 | H251: {=_xlfn.XLOOKUP(E251,Catálogo_Productos!$A:$A,Catálogo_Productos!$B:$D,"producto no encontrado")} -> Mouse Inalámbrico Pro | I251: Accesorios | J251: 45 | K251: =F251*J251 -> 45 | L251: =K251*(1-G251) -> 42.75 | M251: =K251-L251 -> 2.25
K252: =+SUM(K2:K251) -> 328600 | L252: =+SUM(L2:L251) -> 316081

Sheet Catálogo_Productos
A1: SKU | B1: Producto | C1: Categoría | D1: Precio_Lista
A2: PROD-101 | B2: Laptop Pro 15 | C2: Tecnología | D2: 1200
A3: PROD-102 | B3: Monitor 4K 27" | C3: Tecnología | D3: 350
A4: PROD-103 | B4: Teclado Mecánico RGB | C4: Accesorios | D4: 85
A5: PROD-104 | B5: Mouse Inalámbrico Pro | C5: Accesorios | D5: 45
A6: PROD-105 | B6: Silla Ergonómica | C6: Mobiliario | D6: 280
A7: PROD-106 | B7: Escritorio Elevable | C7: Mobiliario | D7: 420
A8: PROD-107 | B8: Audífonos Noise Cancelling | C8: Audio | D8: 190
A9: PROD-108 | B9: Micrófono USB Studio | C9: Audio | D9: 130

Sheet Tablas Dinamicas
B2: canales de distribución más rentable en términos de venta neta
B6: Etiquetas de fila | C6: Suma de Total_Neto | D6: Suma de Total_Neto%
B7: Sitio Web | C7: 54280.25 | D7: 0.17172892
B8: App Móvil | C8: 65014.75 | D8: 0.20569016
B9: Tienda Física | C9: 84800.75 | D9: 0.26828803
B10: Distribuidor | C10: 111985.25 | D10: 0.35429289
B11: Total general | C11: 316081 | D11: 1
B17: impacto de los descuentos sobre la facturación final de cada canal
B19: Descuento_% | C19: (Todas)
B21: Etiquetas de fila | C21: Suma de Fuga de ingresos | D21: Suma de Fuga de ingresos%
B22: Sitio Web | C22: 704.75 | D22: 0.056294432
B23: App Móvil | C23: 2825.25 | D23: 0.22567697
B24: Tienda Física | C24: 3794.25 | D24: 0.30307932
B25: Distribuidor | C25: 5194.75 | D25: 0.41494928
B26: Total general | C26: 12519 | D26: 1
B32: Variación de ventas netas según ubicación geografica
B34: Descuento_% | C34: (Todas)
B36: Suma de Total_Neto | C36: Porcentajes
B37: Etiquetas de fila | C37: Sitio Web | D37: App Móvil | E37: Tienda Física | F37: Distribuidor | G37: Total general | H37: Total general%
B38: Barranquilla | C38: 9015 | D38: 8694 | E38: 10120 | F38: 13881.25 | G38: 41710.25 | H38: =G38/$G$44 -> 0.13196064
B39: Bogotá | C39: 7890.5 | D39: 4490 | E39: 13669.25 | F39: 17426 | G39: 43475.75 | H39: =G39/$G$44 -> 0.13754623
B40: Cali | C40: 7365 | D40: 14352.25 | E40: 11970.5 | F40: 16916.75 | G40: 50604.5 | H40: =G40/$G$44 -> 0.16009978
B41: Medellín | C41: 9695 | D41: 13869 | E41: 17720.5 | F41: 9437.25 | G41: 50721.75 | H41: =G41/$G$44 -> 0.16047073
B42: Pasto | C42: 7851 | D42: 8704 | E42: 2446.75 | F42: 32569 | G42: 51570.75 | H42: =G42/$G$44 -> 0.16315675
B43: Bucaramanga | C43: 12463.75 | D43: 14905.5 | E43: 28873.75 | F43: 21755 | G43: 77998 | H43: =G43/$G$44 -> 0.24676586
B44: Total general | C44: 54280.25 | D44: 65014.75 | E44: 84800.75 | F44: 111985.25 | G44: 316081 | H44: =+SUM(H38:H43) -> 1

Sheet Dashboard KPIS
B4: Kpi interactivo
B6: canales | C6: Descuento % | D6: venta neta | E6: N° Transacciones
B7: Distribuidor | C7: 0 | D7: =SUMIFS(Ventas_2026!L:L,Ventas_2026!D:D,'Dashboard KPIS'!B7,Ventas_2026!G:G,"="&'Dashboard KPIS'!C7) -> 56935 | E7: =COUNTIFS(Ventas_2026!D:D,'Dashboard KPIS'!B7,Ventas_2026!G:G,"="&'Dashboard KPIS'!C7) -> 38
B9: canales | C9: Descuento % | D9: venta neta | E9: N° Transacciones
B10: Sitio Web | C10: 0 | D10: =SUMIFS(Ventas_2026!L:L,Ventas_2026!D:D,'Dashboard KPIS'!B10,Ventas_2026!G:G,"="&'Dashboard KPIS'!C10) -> 44550 | E10: =COUNTIFS(Ventas_2026!D:D,'Dashboard KPIS'!B10,Ventas_2026!G:G,"="&'Dashboard KPIS'!C10) -> 37
B12: canales | C12: Descuento % | D12: venta neta | E12: N° Transacciones
B13: Tienda Física | C13: 0 | D13: =SUMIFS(Ventas_2026!L:L,Ventas_2026!D:D,'Dashboard KPIS'!B13,Ventas_2026!G:G,"="&'Dashboard KPIS'!C13) -> 43785 | E13: =COUNTIFS(Ventas_2026!D:D,'Dashboard KPIS'!B13,Ventas_2026!G:G,"="&'Dashboard KPIS'!C13) -> 31
B15: canales | C15: Descuento % | D15: venta neta | E15: N° Transacciones
B16: App Móvil | C16: 0 | D16: =SUMIFS(Ventas_2026!L:L,Ventas_2026!D:D,'Dashboard KPIS'!B16,Ventas_2026!G:G,"="&'Dashboard KPIS'!C16) -> 34190 | E16: =COUNTIFS(Ventas_2026!D:D,'Dashboard KPIS'!B16,Ventas_2026!G:G,"="&'Dashboard KPIS'!C16) -> 34
